solarhouse/__init__.py
solarhouse/building.py
solarhouse/calculation.py
solarhouse/export.py
solarhouse/helpers.py
solarhouse/settings.py
solarhouse/thermal_element.py
solarhouse/thermal_model.py
solarhouse/thermal_process.py
solarhouse/version.py
solarhouse-0.0.4.dist-info/METADATA
solarhouse-0.0.4.dist-info/WHEEL
solarhouse-0.0.4.dist-info/dependency_links.txt
solarhouse-0.0.4.dist-info/top_level.txt
solarhouse-0.0.4.dist-info/RECORD
