Metadata-Version: 2.1
Name: solarhouse
Version: 0.0.4
Summary: package for calculate solar power what you can get                on surfaces of building by solar heat collectors
Home-page: https://github.com/yaricp/py-solarhouse
Author: Yaric Pisarev
Author-email: yaricp@gmail.com
License: UNKNOWN
Platform: UNKNOWN
Classifier: Programming Language :: Python :: 3
Classifier: License :: OSI Approved :: MIT License
Classifier: Operating System :: OS Independent
Requires-Python: >=3.6
Requires-Dist: numpy
Requires-Dist: scipy
Requires-Dist: trimesh
Requires-Dist: pvlib
Requires-Dist: pandas
Requires-Dist: matplotlib
Requires-Dist: mpld3
Requires-Dist: shapely
Requires-Dist: jinja2
Requires-Dist: netCDF4
Requires-Dist: siphon
Requires-Dist: tables
